asyncweb/__init__.py
asyncweb/routers.py
asyncweb/views.py
asyncweb-0.0.2.dist-info/METADATA
asyncweb-0.0.2.dist-info/WHEEL
asyncweb-0.0.2.dist-info/top_level.txt
asyncweb-0.0.2.dist-info/RECORD
