Metadata-Version: 2.1
Name: asyncweb
Version: 0.0.2
Summary: Asynchronous restful API
Home-page: https://github.com/lvyunze/asyncweb
Author: yunze
Author-email: 17817462542@163.com
License: UNKNOWN
Platform: UNKNOWN
Classifier: Programming Language :: Python :: 3
Classifier: License :: OSI Approved :: MIT License
Classifier: Development Status :: 3 - Alpha
Classifier: Operating System :: POSIX
Classifier: Operating System :: MacOS :: MacOS X
Classifier: Operating System :: Microsoft :: Windows
Classifier: Topic :: Internet :: WWW/HTTP
Classifier: Framework :: AsyncIO
Requires-Python: >=3.6
Requires-Dist: aiohttp
